{"264589": "lxj", "216377": "hkimi", "285311": "miminashi", "231218": "oohito", "223343": "ywg", "254982": "NICKJK11", "264391": "ASLM", "283416": "tamie", "232603": "catalyst", "266239": "bigads", "203718": "jun_y", "260228": "Kwansei", "244827": "DrMath", "224810": "doodoohead", "227832": "ADINA", "216889": "oba", "216863": "m_yusuke", "207202": "joey0415", "299013": "PERCE-NEIGE", "295303": "Rehaan", "202132": "gamerkeeg", "215110": "SpriteMaster", "223387": "tootinyman", "247981": "Nemoracer", "217769": "xota", "248854": "Zoomreddin", "249321": "mozar", "248903": "drew22", "271452": "nadnerb", "249406": "seagoon", "204823": "2222", "274916": "novice27b", "267162": "gabrielgabriel", "231214": "scratchisthebest", "281383": "ferilgater3000", "212429": "repo", "272490": "nXIII", "279461": "olly2002", "297638": "happyman1", "237140": "kyler7", "294354": "Gamefan888", "201058": "BenDaMan", "272878": "Solarbuddy", "210965": "schoman3", "213256": "scratchem", "293240": "Andrew360", "235628": "krish15", "217121": "kerbykong", "205508": "mikkel500", "219154": "MrMokey", "210703": "june12th1968", "246290": "scmb1", "250602": "taddl", "298545": "jakeemma", "215102": "OldWheezerGeezer", "291610": "Subh", "270443": "dgfnd", "253819": "Pika9876", "271447": "Diasty", "246523": "chaoticmaster", "289185": "Platty", "299855": "Mink2", "270468": "werdna1", "232311": "bobaba", "249782": "scratchpop", "294490": "Grania", "279566": "Xaviaz", "231165": "princeeric", "239598": "upt", "221270": "gangsterqueen1234", "200323": "Z1FYTests", "231412": "LOZELDA", "271462": "Survivorduck", "200276": "roijac", "214880": "bobbybee", "226355": "GP1", "211130": "Santiagoo", "279261": "LS97", "288297": "llamallama", "289036": "Supersil", "221227": "aliG3x3", "240511": "Emberclaw", "221160": "steke", "217347": "2194MUD", "283974": "1675", "278920": "Striker-11", "298447": "guyman55", "290306": "SamaraBostic", "235424": "keghani", "287803": "dragonforce100", "266530": "darkchaoschao123", "239656": "MOVIES4YOU", "245112": "-Gabby-", "237671": "Masterp", "240219": "mathematics", "293815": "-SkyStar-", "213031": "777w", "208141": "Konis", "258834": "pinochio", "240988": "Bailey365", "229933": "ev999", "272822": "GoldenMagic", "286612": "ahaanomegas", "269566": "narutocreater", "204976": "benny57", "244221": "daine26", "266026": "Thilo", "239997": "mshul", "273918": "metschamp", "273494": "MastaD0001", "245770": "hboy", "248091": "kobie", "230597": "tritri", "262896": "abc-freak", "203552": "zbugni", "225175": "Gandalf_der_Graue", "203536": "Richanator", "280191": "kevinerdiza", "279530": "PuppyDog01", "281873": "codamax", "277619": "bobthejoe68", "287832": "amurphy964", "278575": "ke1235", "209762": "boofly", "225006": "bruneydog", "265961": "mrspraulsclass", "229827": "candy0503", "211303": "WarioX", "221191": "smandoli", "215696": "nintendo_fan", "216233": "dialga1234", "298246": "COOLcats312645", "215264": "Boris_", "204623": "justjess678", "295274": "AtomicBawm3", "294524": "akita", "295878": "owetre18", "272440": "caleighc", "275848": "PW132", "273396": "AhmedAyman", "285326": "Pc_Freak", "231440": "cpumaster930", "210704": "quoteme13", "246267": "joeylego", "280068": "GarSkutherGirl", "222315": "pcmags", "282511": "samid11", "239954": "pingpong10", "210383": "snowsquare", "254476": "maail", "299732": "kingdragon", "275711": "agscratcher", "225852": "jessieandfall", "295079": "starspeed", "291873": "Willig", "251120": "olic32", "216744": "Lukia26", "249453": "abigailg", "293808": "FaribaultGiftedKids", "221408": "katti415", "273026": "wscs", "222311": "christian9", "202673": "eeve11", "292527": "MrMunchkin", "294019": "Hidan09", "297756": "JamesX", "230391": "micma", "288780": "mariodog22", "260625": "metal509", "271760": "Ziquallx", "271272": "Lolersk8s", "237826": "PoDo", "285965": "vitor_sp_fernandes", "264399": "motto-motto", "278304": "oliviad", "215293": "marketa", "291745": "beakyiwan", "293664": "frankdude", "206045": "HamsterMan2000", "281135": "HCN", "269589": "solojack", "223366": "etheli", "203313": "Prestige", "256439": "Kozuma3", "260593": "fafcater", "269370": "beatmygames", "285299": "scratchdancer97", "240838": "jkbluepheonix123", "253694": "Slinky", "290717": "pokeywokey", "245165": "snipper9", "296029": "horsegoddess", "216769": "iamjill101", "263763": "Tzine", "217422": "celloguy123", "283250": "sylasvondrac", "288917": "turtwig360", "277871": "stoneface", "240297": "WeirdF", "290481": "sohk", "272285": "bananamonkey", "288749": "ell98", "264775": "jake451998", "259282": "JOEJOE2", "254143": "amyjrose99", "299823": "tezcatlix", "250263": "Thorntalon", "261317": "purpletofu", "262763": "itchyscratch", "284370": "lilly62", "230807": "matt99", "222577": "Mbear", "234076": "quint", "286929": "krazykookoo", "297569": "Kiladako-T19", "296030": "Mickyboo", "284744": "andydongwook", "287212": "apple0516", "224153": "joethan", "255514": "micycle2", "250712": "boogawk", "286222": "Falcon9132", "279972": "Imic", "273406": "ava06", "280110": "pookie98", "299541": "Isometric", "243624": "ElPapa", "287878": "flamehawk", "248744": "exotic", "245890": "All4one", "228635": "lightingandskulls", "280132": "norfilax", "231178": "nknknk", "239443": "Spinorex", "294300": "Earthgirl3000", "278115": "2k8naruto", "256248": "Skiboy", "237226": "wekkdore8", "292817": "News-guy2", "284524": "scratchday", "224632": "ScratchDude101", "286922": "BulletL", "264549": "scratchguy125", "227718": "jimbo2802", "220145": "kgordon", "280932": "mannster", "275540": "matey", "284971": "Joshua1123", "285339": "Bannan233", "237806": "BobbyMan", "284595": "woodman", "272045": "Ultimatium", "205328": "frogger3140", "210491": "zhamster", "275281": "Robojam200", "283744": "DoodySprites", "281708": "Crazypenguin123", "254032": "jimihendrix09", "239440": "Ilovestarwars2", "275722": "frodoatchicago", "277870": "dakota84", "241631": "dav09", "225437": "Dragonflower", "279820": "Bluedude1", "275764": "TwinkleFoot", "269414": "bleepo", "277260": "unbreakablexlmax", "277706": "Leesha300", "241782": "dancept1", "254124": "ActionCat210", "265411": "athletical10", "274214": "kinggurgle", "250934": "Leafpaw", "256034": "piko_12", "256310": "theonionsandpickles", "267244": "adamsandler", "233242": "pent9", "270340": "gothic_hawk666", "270864": "ScratchMusicGroup", "210117": "lijuexian", "259200": "BrendanAlford123", "263503": "Orocles", "268269": "MrTeacher", "220527": "Djmc80", "236654": "zupunupi", "237727": "sph12", "215707": "when-u-r-evil-fan-", "257182": "Karatekitten", "258983": "sockface", "242810": "louisrulz122", "203411": "StBernard17", "234290": "Comment_Man", "250329": "KalinaStar", "258978": "ashkon_p", "223968": "SuperKG", "255506": "gwin65", "254438": "djdante", "257454": "doggie001", "256962": "11yancazosj", "215036": "lifeleaf", "256122": "Paddle2SeeFanatic", "247638": "s543154", "253380": "mkreitler", "254282": "peytonsbessiecarcar", "247707": "i_a", "248102": "doded1", "225306": "yoda44", "249721": "zoingo8", "229679": "coolcole", "237573": "KRei19", "237169": "Gam007", "237569": "ros126", "207724": "ositapink", "216402": "hicups", "232107": "itsprem94", "226635": "zb8", "239224": "Glorp", "217902": "gorge8921", "210959": "sniperdude", "217452": "nionwar", "219055": "Diamondstar", "239250": "Joolah", "208737": "Sonnywithachance", "227190": "smallstuff", "239936": "stoncoo", "227065": "dzanichelli", "222781": "TheCatcher", "240506": "moviegal911", "222015": "anniebonebrake", "230122": "mudnose", "238813": "lilwayne973", "238159": "bainbridgeunicorn", "229342": "BobJr250", "238213": "heracrossrules", "226248": "Animal_of_the_week", "208484": "RUMCHEERYPOOPOO", "232681": "princess17", "231244": "DarkEnergy", "231785": "yagovisk", "231726": "Tylong", "229205": "ploto_scratch", "214676": "tk40n12", "230271": "Monkey-Head", "229843": "alyssaforever", "209848": "Firefairy24", "227761": "jayfresh123", "225696": "SWindlerne", "207010": "Pichuperson", "211032": "degscratcher", "222387": "moonly", "211016": "BRAWLME", "224799": "HAL-1701", "212919": "Inferno-Maniac", "214849": "jman123", "218909": "sk8erboy", "209656": "brinley24", "221261": "dionfullwood", "218646": "lollypopzere101", "201944": "al1996", "213246": "Semester", "219763": "HyperScape", "210563": "blackturtle", "204139": "bugsbunnyj", "218500": "11kirby", "216007": "SeeJay92", "216590": "grenadillo", "210841": "elgren5", "214328": "Rockhopper2175", "211093": "avatarl8", "208078": "InterGalactic", "204547": "pgtubre", "211791": "irtysh", "211722": "Mike747", "208073": "mooman2", "210902": "Runaway4ever", "210112": "billyofeng", "210604": "LegendaryGuardian", "209946": "SuperStudio", "200789": "canadaguy", "209907": "I_Love_Christmas", "208794": "bosox_test", "209310": "Bentheneighbor", "201845": "Supertux3", "208640": "scampers77", "209212": "MDX83", "209006": "Scratchmaster01", "208839": "ginny1234567", "200109": "bosox297", "208545": "MarioKart6767", "208208": "Genhard", "200599": "cameron_T", "202154": "13bennja", "203830": "Pipsy", "202450": "Ninjaboycp", "200166": "shawt", "200624": "I-LOVE-MAJORETTES"}