{"2813063": "Reshie", "2809500": "powapowa", "2834508": "Arsu", "2866642": "mmkoala", "2828900": "yu_oga", "2817380": "ilovemariokart", "2882694": "tento_anoato", "2871303": "pancakes19", "2812514": "K-K_Sub", "2803633": "LittleBean", "2842842": "victoriustecnic", "2869378": "bitbyte2013", "2838017": "team_vega", "2813141": "dorian676677", "2852444": "danielhal", "2831783": "nemoiscool", "2875247": "Tobyakira", "2849124": "ishmason", "2881193": "Dhilly", "2846140": "Jeditwo", "2845787": "girlsarecool", "2888542": "magnus04", "2811991": "bronco18", "2827892": "togipi", "2853179": "creativecreeper", "2833523": "s200901131", "2841198": "Bubbles166", "2894758": "Jconway1", "2865114": "cerebrostorm", "2850047": "puppyok77", "2837542": "pah05", "2893464": "funisscratch", "2856383": "ohlinator", "2881979": "flamethrower21", "2827582": "Getafix", "2811088": "asdase", "2874157": "israch", "2833419": "Mariano42", "2846118": "SKATERIKE", "2812405": "Aireilbon", "2894442": "visionbonwoo", "2869377": "jfanime", "2835672": "ylvaj0504", "2841432": "Shekye", "2862084": "Zeila200", "2887879": "MustardCustard", "2881282": "scratch575", "2861329": "NFD712", "2814461": "tallthegamer101", "2876304": "xXTheThingXx", "2810583": "RedNeckSideKick", "2855475": "luna2687", "2828104": "epark", "2820454": "BasketballForLife", "2813153": "eyepopper360", "2832127": "yamu1001", "2860697": "ragecult", "2845864": "rtftts", "2837832": "pikachu11", "2824852": "sashabunny101", "2817289": "doctor-x", "2819212": "MathewC", "2849885": "Christiand1014", "2856394": "balletmovies", "2871324": "follow4follow", "2888169": "falcon4", "2825707": "bountyhunterx-3", "2872031": "CR87863", "2889781": "OrigamiGal", "2816858": "vanobras", "2874362": "shigloo", "2867903": "Fudge26", "2897648": "DTROLL44", "2851805": "timodude", "2847727": "flintandsteeltn", "2848152": "23430", "2803082": "picopaper", "2869495": "trevorspace", "2848552": "Devonk", "2806502": "epar5294", "2803607": "maxers", "2873653": "venomous-squirrel", "2814006": "tagggz", "2820607": "bobsmydog", "2844249": "Pokemon_master_max", "2886432": "rlspicypeppers", "2850089": "JO-YO", "2841291": "lilhoginpitt", "2806425": "ryangreat", "2815070": "Giyun", "2841345": "Rainmask2309", "2840665": "sfsydneyt", "2875695": "Bunnies1234", "2842687": "ijjypop", "2806476": "arinekim", "2866545": "joejoeL", "2802613": "lukyduky", "2855882": "ssbear", "2867252": "Papaya05", "2874008": "Penguin5664", "2812803": "luigiluigi1234", "2862178": "gemomania", "2802256": "java35", "2816981": "cadencecopy", "2881531": "geobee900", "2840124": "DUMB200", "2882529": "spyro12675", "2814642": "DolfanXan", "2813209": "N1njabert", "2826346": "h51769", "2850046": "caleb_ninja", "2833352": "coocoo333", "2838878": "simba777", "2865571": "snipermaher", "2843933": "jenwilkel", "2808346": "benjamoga", "2842528": "pjan", "2833443": "Izaberu-chan", "2829695": "sfalexish", "2882886": "Gardevoir-", "2893885": "P2-S2", "2883537": "bnbluestein", "2827520": "werearewe", "2870714": "crankspl", "2836940": "ecarlisle", "2897663": "tepig46", "2825964": "sfbrookeb", "2851186": "unicornsrus", "2841590": "minecra", "2844067": "sammy2004", "2871308": "Class12321", "2881938": "Ranikk", "2876517": "Hudsonshah", "2854684": "fionak18", "2899971": "Dr_Minecraft", "2831745": "meowmeowkat", "2802737": "Firestar5166", "2850117": "Chyahiy", "2813695": "tumblebolt", "2802178": "lcftf", "2873804": "ajdigs", "2812893": "pokedragon989", "2835420": "moontb", "2873638": "harrybear", "2812144": "legochimafan", "2802730": "dzr2003", "2844707": "robo9", "2843699": "SparkleFilm", "2843475": "gilad3345", "2841034": "sfdanielm", "2860477": "sfellan", "2819983": "GeorgeEPickle", "2808483": "MintyMoo", "2899965": "applepiesleth", "2897268": "say4640", "2898573": "jmarin38", "2807743": "hiblitzx", "2868605": "bparsek13", "2882932": "cat103", "2851681": "goldowl37", "2819811": "sfsusieh", "2826877": "Soggywaffle1", "2852602": "EpicWhale", "2897608": "PROGRAMINGisHEAVEN", "2866979": "johnsonjr18", "2819202": "sfnicholasf", "2880819": "natmo10", "2850212": "Turbo-I", "2831762": "bobtherobot", "2899958": "anonymous111", "2865497": "ilikepancakes12", "2899215": "Segarocks", "2887734": "SMDias20", "2891487": "bje31", "2853792": "broku", "2815083": "kat_the_brat", "2839190": "Beanand4", "2825679": "bracken25", "2816000": "Lars_Kern", "2819238": "sftoms", "2886731": "gaylorl", "2815460": "nicobrownmath", "2893613": "Kala30", "2882022": "Scratchlucydog", "2865194": "wezk04", "2899348": "XavierStrike", "2817190": "harith2005", "2882147": "ryankimharrison", "2871746": "tx335397", "2805740": "Ebanisia", "2869768": "Tikolu", "2823249": "omegaa", "2894058": "circuitos", "2845161": "dan55", "2861832": "SoN1c2001", "2832512": "CaptainJbeans", "2845844": "PinkCupcake123", "2803290": "cutecreeper", "2827276": "2034678", "2804764": "smorga10", "2845102": "kuba772kubakuba", "2838086": "piggy924662", "2872083": "purpleflameface2", "2837465": "apple_computers", "2875431": "Svafiadis", "2861229": "bruce5005", "2812355": "Reesecandy", "2827407": "Tux1", "2841019": "sfanishr", "2815279": "legolevi", "2839167": "MustacheMastor", "2896711": "Interni", "2813379": "randomlola", "2814721": "pepsican", "2857565": "majunga", "2814340": "mzdad", "2887025": "Sandstorm5", "2853324": "sonic3retro3", "2816989": "scarpachi", "2873936": "20HunterEt", "2893040": "thezenelson", "2866761": "theultimateguy02", "2859929": "sfnickp", "2878422": "diggingderek", "2871245": "tx318265", "2848232": "Flamboyant123", "2843088": "buzz5", "2823199": "jameshollinworth", "2831179": "pdd88", "2866836": "hawk9510", "2844076": "JSanimator", "2868629": "sporty75226", "2816896": "scratchmaster322", "2873552": "gallery", "2802420": "elakehal", "2829028": "787dreamliner", "2848222": "15nm23", "2874885": "dav5d", "2843019": "slendercam", "2816279": "leow22714", "2864974": "1POLAVARAPU1", "2840827": "CardinalsFan13", "2840672": "sfjamiep", "2874129": "caleb_passero", "2800623": "tennisracket", "2812200": "Spiritspectre", "2834065": "fanbus", "2835591": "nategecko88", "2814253": "hanuman9", "2813178": "hhiddinga", "2864218": "ManicJamie", "2860713": "Atredies", "2803135": "Saphire1234", "2831744": "bombomboma", "2856593": "hachi888", "2845494": "Albus53", "2890200": "Shark-bot_10000", "2853040": "YEE_YOH", "2869387": "jjjadon", "2861178": "miner1345", "2871581": "animator9000", "2819337": "tlawoals1004", "2814931": "thinhong5", "2805952": "sed10", "2811961": "10yearoldgamers", "2859268": "nettalex", "2852233": "roboman56765", "2872925": "Kittycat808", "2809149": "TianaLPS", "2852001": "poplopuk", "2800501": "TrixterTP", "2876338": "astroroman", "2832242": "buttercraft914", "2892200": "DavidM626", "2839361": "babalabashabalaba", "2885183": "Telekinesis", "2803839": "Zusoug", "2827975": "Shadoex", "2813310": "alberto1818", "2890600": "jencoh", "2874567": "SeptaMan12", "2827315": "Dapper_hat", "2821105": "MUDKIPZ12", "2876601": "rainbowdash573", "2813608": "oliversmaster", "2843038": "macklemore453", "2878744": "huds274", "2897593": "king_pokemon", "2821101": "JPB2012", "2811625": "DB_Dynamo", "2862878": "marioman20", "2854062": "scratcher12354", "2814281": "Samrya", "2820671": "Kevinthefish11", "2862130": "Ribsy2009", "2851408": "linu0064", "2830644": "dl2016stm", "2852903": "bennettowen", "2898414": "swillia1", "2814053": "theinator", "2802933": "Snowpea888", "2874330": "heavinsvale440", "2843093": "Scratch13764", "2803253": "programer918", "2858980": "originalbabster", "2831727": "ScratchyToyger", "2833806": "ethandoesmine", "2857789": "dylmine", "2845717": "MegaSpy1", "2803162": "gabe19082", "2845283": "Windows998", "2874386": "ilovewolfys", "2889773": "spacekirby", "2846693": "chuckoli1", "2844274": "mylittleponylover", "2854149": "blee1", "2836910": "kingsley2002", "2860766": "HypnobraiGeneral", "2848024": "coolguy95", "2891460": "trikster30", "2858699": "thomasg18", "2853867": "xXCornDogsXx", "2879514": "martin62", "2860405": "sebitommy123", "2816223": "japirate777", "2801618": "pikachuguy12346", "2831445": "MasonMinercraft", "2820687": "jun844", "2866341": "imvietx", "2862004": "FoldorFly", "2821413": "madrigaldavid", "2802843": "UltimatetheHedgie", "2875487": "phoebe3460209", "2867499": "Mr-Angry-Fruit13", "2853777": "cocicat", "2810494": "coolguy0513", "2810033": "witus13", "2882925": "emeraldofepicness", "2818884": "CeasuimStudios", "2825975": "sfmorgane", "2880123": "DADSTOP", "2827486": "ghastendo", "2867225": "Sparki34", "2825693": "GojiCheetah", "2835435": "cuddles9260", "2816417": "MBS2004", "2854498": "minecraft_6", "2893473": "tommy2003", "2838065": "deawesomeMEEP", "2803244": "Random-Stickmen", "2852589": "Erizo-Blue", "2837657": "Watson_Chao", "2881897": "007279", "2875188": "adamkid09", "2846116": "irving2", "2874333": "tonysarah000", "2859759": "avertullo", "2834013": "saprojectklas", "2813226": "ScratchEli12", "2856256": "darshan2003", "2817322": "ColonialCyborg", "2829890": "piguinrulist", "2885011": "moofish", "2812760": "vampirenighthawk", "2866744": "Themagickscat", "2857088": "Linea02", "2841669": "jayjayjay3000", "2870210": "Whatdoesthefoxsay29", "2892693": "ElementalStudios", "2827939": "Yang-Yang2", "2862955": "MCblondie23", "2855443": "Elitob", "2808052": "starfallp", "2878011": "ridgecrestelem", "2814099": "drwho3", "2866988": "jacowaco", "2885126": "Zappy1333", "2885014": "coasterguy360", "2825059": "violet012", "2899064": "Flashomatic", "2875685": "cool1987", "2856528": "pcbrams", "2827688": "bobpoo3", "2845953": "kirbywavern", "2820647": "GGTheScratchmaster", "2815511": "upelly", "2856409": "seadragon02", "2880940": "SebothebestScratch", "2849273": "ski_puppy", "2834833": "axaaa001", "2834827": "sasea003", "2831897": "johnandersen", "2822744": "loveshuang06", "2850847": "Thebudderscratcher", "2825080": "violet13", "2855645": "Bloodshoteyes", "2844134": "minecraft407", "2801691": "lmsp7cm", "2873938": "TomPallister", "2844804": "maxiscratch123", "2896611": "bainer101", "2870273": "Joefth", "2897302": "44Hydras", "2812775": "Supercloud15", "2856093": "LiamRules", "2806288": "LiquidGP", "2844401": "elementkid989", "2896352": "Narucci", "2825589": "Lucario2002", "2821567": "steve100", "2816267": "Sonnyismario", "2834839": "asbja001", "2817194": "Woofcat", "2803090": "fairfaxel", "2890705": "jackieman9", "2877995": "papayasm74", "2862484": "Coolguy106", "2823043": "scratchtastic123", "2899853": "NBABASKETBALL1", "2864086": "dukedroklar", "2821104": "minecraftbros17", "2892923": "HasturMaster", "2864941": "pins12346", "2848116": "GAMEMASTER47", "2842230": "zflame109", "2871533": "popyofox24", "2843182": "pikachu1984", "2810123": "wolfclaw12", "2807394": "Bertiechap", "2841725": "randomhouse4", "2845995": "nblount", "2856530": "blbrams", "2850968": "gamerman0", "2849136": "Helper007", "2897116": "ManhasProgramMethod", "2896738": "corbin433", "2817330": "mewmewpower1", "2882111": "piguy10", "2806903": "TRI-GENERATION", "2873437": "GamingZoner", "2813097": "ImmortalSentry", "2854915": "Fierycreeper", "2868794": "HECTOP", "2836413": "pokemaniac34", "2830358": "flynn2019pw", "2897442": "eskee525", "2852380": "perhugo", "2809410": "Eob11", "2802583": "simon958", "2893365": "Samsquatch", "2864513": "TheScratchLegend", "2898887": "sharkkeeper", "2827161": "googie212", "2824306": "tyson521", "2844092": "Walter51", "2882851": "Cat_Call", "2812002": "scooter10", "2881662": "var10wiz", "2878875": "366653", "2826296": "eevee155", "2850897": "minecraft_5", "2857199": "johnheredia", "2827164": "Mr_mastodonfarm", "2868940": "DrakanPL", "2841302": "MemoByte", "2824532": "JeremiahMacDonald", "2866627": "qasimstar123", "2845905": "CTEvans14", "2816745": "jlee049", "2831511": "Easterbunny_iz_rel", "2871056": "awsomeed", "2876330": "TheGameBuilder", "2861873": "mathcats", "2874389": "Bow_II", "2869500": "TEDDYGRAMS", "2844311": "liangliangsong11", "2812424": "warriorsfirestar", "2823949": "cheekysniper", "2871797": "rdproductions", "2822194": "XXThePhantomXX", "2862268": "Rz2750", "2866874": "KitKatKate100", "2832574": "KILLERVEGETA", "2848204": "Australia123", "2873612": "blahblah101", "2881197": "stuffrocks", "2892921": "LanceLovesMinecraft", "2820676": "loripanda07", "2882831": "flashdashhorse", "2890763": "S11ENTHAWK", "2844184": "cookie208", "2811977": "Daphy_Lover", "2815314": "Spitfire_71", "2881240": "yobananaboyscratch", "2820148": "loebas", "2812925": "Streetpete1", "2876028": "ColdPolarBear", "2803248": "ses123", "2869517": "liampmac2002", "2882400": "ZeusTheThunderer", "2829146": "descratchmaster", "2841964": "ipzy", "2809334": "chariotmaster111", "2874634": "damerster", "2803510": "boomman222", "2836674": "1romeo", "2846457": "Zandrock", "2826538": "spraoigamesmaker", "2880542": "HoveyTech", "2879701": "Hyperman500", "2875069": "lolw", "2844287": "thingmaker", "2872582": "YakMaster", "2845812": "Darcythecat", "2802836": "TheB0SS37", "2844626": "bluepopsicle", "2861381": "flyer74", "2811876": "dylanbh", "2811172": "secrethide1", "2895383": "cb1502723", "2817160": "annagid", "2846043": "MagicPencil", "2805901": "maumau02", "2877917": "Dragon5786", "2822067": "caboben", "2833034": "Ashlea25", "2888109": "Opihinalu", "2846700": "toothless1", "2832377": "Aboyblack10", "2850260": "blobby212", "2804835": "wisedoubt", "2839790": "mikelinscratch", "2872282": "8discobusy", "2836497": "pookman4", "2853035": "FlashWing11", "2894185": "lily_love", "2833423": "CreativeAshe", "2816859": "scratchy1024", "2893079": "RobomanDude", "2895753": "hut19", "2853969": "LamaBomb", "2858739": "punk_monkey24", "2868124": "Samueljh", "2842637": "Cleverbrain", "2876491": "UNKNOWN0", "2867100": "ifollowadam", "2886406": "TheCoolGamers", "2896418": "Hettas", "2844530": "BatProductions", "2843322": "cpmaster101", "2837115": "200840", "2810958": "firejoseph1234", "2878469": "The_Epic_Medic1", "2834812": "bobd4935", "2838125": "chrislee777", "2810944": "birdhunt", "2816357": "tacoman9241", "2859183": "Aragorn5986", "2848619": "batmanwithdev", "2890794": "froto26", "2844317": "CEOofApple", "2850103": "RememberNovember", "2820551": "TheBlueHatMan", "2890784": "gjames788", "2893197": "creepypasta_fangirl", "2871811": "Jaden05", "2896433": "phabletcrunch", "2858841": "-Ravenfeather-", "2837881": "Boybobka", "2839633": "piiscool1", "2832009": "Dill6274", "2800733": "OGHadeZ", "2881366": "FruityGrrl", "2865120": "CocacolaCanyon", "2881953": "CaptainAwesomeness", "2884808": "Danlar_Follow", "2881285": "everythingelse", "2872223": "2078kgy", "2847768": "Mantor", "2842803": "Tylowinger", "2874466": "Aliex", "2873278": "PixelPerfect", "2872935": "xxCutexChicxx", "2868002": "Cubelet", "2832121": "katelyn-ast", "2855425": "Ecodium_Enterprises", "2848754": "Awesomepotato", "2859533": "GhostToker6565", "2856804": "kittykat123meow", "2855751": "Live-Life", "2856021": "Jester82TV", "2855259": "demaru", "2847285": "Trezpasser", "2845973": "EpicFollower", "2844041": "NETprod", "2843822": "phil4074", "2821335": "hiccup_gaming", "2842329": "coolProgramer45", "2837826": "Percy_Jackson1001", "2829729": "STORMdrake", "2829403": "dragonsun", "2803336": "Elmray", "2806902": "Chis1901", "2807550": "Misha206", "2811228": "FreeBsd", "2801289": "mahler_thomas", "2803976": "Lonewolf555", "2803088": "Funbomber", "2803114": "Scratcher_", "2800464": "A_Follower", "2854044": "powercon5", "2820974": "giftbaby04", "2834353": "Jqualey", "2850257": "ANEvans14", "2808572": "kanashimi", "2881540": "mars10", "2846861": "MoonlightAnimations", "2814220": "Pomchi76", "2809592": "cooldude8802", "2897168": "RandomEpicness", "2860339": "lob12", "2843117": "GANDAM5", "2877166": "Kazpon", "2876183": "krett12", "2833711": "ScratchehBepper12v2", "2816978": "Followbot", "2830849": "clarence112", "2835939": "MARPAT", "2812593": "HanahOuO", "2813941": "carrilne", "2817119": "prettywaterlily", "2862603": "LOVE-MATH123", "2843920": "Deerleg", "2842053": "Hollygator", "2800508": "Vinthor", "2806499": "bang1234", "2831301": "sfmaeleighe", "2811407": "mouseytricks", "2811371": "rabbitsrock", "2836862": "LWCinPWC", "2881574": "Scratch_Tutor", "2830266": "pigletdiglet", "2840832": "Shadow671", "2875907": "StalkerNinja", "2833098": "Codster39221924", "2803693": "ABCScratch123", "2832845": "raydioactive", "2824353": "Imi99", "2812757": "Butter_brother", "2805769": "scrachi101", "2837473": "tsdgamer", "2859336": "DeThKa", "2873983": "cgleopard", "2897495": "Blueshark_", "2891256": "FireStar05", "2851832": "iholt", "2803785": "horse-123", "2843466": "sariko", "2815696": "The_Follower", "2894355": "Miltrocksairborn", "2841925": "Treecko008", "2830891": "wolfgirl1", "2850024": "dsosa29", "2839367": "dertmert", "2840496": "pikachu27", "2816563": "copemanm", "2838049": "MustangHorse", "2871767": "skittleman65", "2843929": "theobenjamin", "2837545": "zadden", "2816940": "ChoclateQueen", "2871722": "aspenstar", "2887907": "bobnaclh2o", "2811274": "weetikveel", "2823236": "smartymarv", "2871525": "mol2", "2803781": "tmits57", "2860212": "MISSYKITTY", "2871094": "BridgetteTheDog", "2898442": "grimsleydark", "2812226": "scratch___loverzzz", "2880189": "FlutterPal", "2843359": "Awesomekids3", "2888030": "scratchtj", "2846681": "FaithScratch", "2870526": "Dolphin27", "2898985": "ajejugd", "2836022": "AnnaBee", "2825655": "Ziggy_poppy", "2827013": "_Athena_", "2810090": "lioncupcakes", "2875166": "codingcake", "2845388": "dan2009", "2808133": "kitten80", "2875215": "Firefly88909", "2866145": "TheCentipede", "2808586": "mia350", "2848284": "ginny5000", "2821441": "Tigerstreamwarrior", "2813572": "Ewazor", "2866119": "loganpb1", "2883372": "XxRavenheartxX", "2805499": "1chowell", "2812554": "Amelia2898", "2872556": "sonicMLP123", "2813279": "roseyandu", "2803901": "erickson123", "2815659": "NorthEast", "2816541": "FollowXx", "2846168": "cutestbunny", "2837091": "charil456", "2805014": "MarryAnn", "2860598": "horsegirl2003", "2848270": "jammiedogers", "2850973": "osietekudasee", "2871517": "Ex-Stick-45_", "2826882": "aquos", "2817953": "kmaim", "2808430": "FUN1012038", "2882866": "kotoya", "2872884": "m_zumi", "2867560": "hideyoshi", "2849460": "makorra42", "2830384": "Lillibob2003", "2836645": "noahdaigle", "2856269": "thebossyo", "2821932": "kevman34", "2840670": "sfevanp", "2876208": "smilingbutt", "2815048": "Game--Maker", "2814909": "GameMaking", "2899807": "FlashwindWarrior", "2852846": "Star987", "2825849": "glicth", "2876541": "MuscleMan999", "2866156": "EpiCoolMan", "2808300": "emmag159", "2871665": "Braixen", "2871859": "FlowTest", "2873663": "konradel", "2882136": "MagnetMan4", "2873252": "deciple", "2814472": "10513claypit", "2845273": "Unlocked2", "2813109": "MMStudent-04", "2863178": "Tigo9", "2855396": "pk_starstorm", "2892398": "animaljam2013", "2846399": "emy9123", "2839406": "1041", "2811793": "TastyPieCherry", "2856285": "soso24", "2887976": "dr-mario", "2853735": "snehalm_123", "2871120": "Horseygal02", "2816897": "kking17", "2899550": "crazyelephant123", "2839001": "julia29", "2837830": "wazzo_tv_fan", "2873693": "Tig08", "2817886": "gramin_master", "2846544": "takato0704", "2844165": "TheWindWak3r", "2808702": "imored", "2833659": "blue_violet", "2820353": "Heilong", "2873017": "mktsome", "2852043": "The-Awesome_12", "2832686": "gravity-falls", "2870196": "BOSSOFMONKEYS", "2843324": "cannon706", "2815088": "Mellowjello", "2821695": "coler707"}