{"3922739": "asa4545", "3993412": "catmanG", "3929333": "hoozuki", "3940676": "azennto", "3955127": "yukikentotomoko", "3993708": "kuruku", "3972628": "tsukugaku", "3995611": "karanats", "3956715": "ieame", "3945734": "rits20100650", "3917478": "samirak", "3996909": "nanatti", "3952749": "yossiy", "3928479": "awey", "3922456": "machapyon", "3948778": "koDoz", "3949801": "neko2002", "3944858": "s213r021", "3997561": "sasakilemonte", "3993498": "junsei", "3925053": "Mikkun", "3940106": "suziyonyon", "3978135": "tltl2000", "3954822": "dunk_fire", "3949677": "41229674", "3957593": "meepu", "3910087": "ypsva", "3925772": "CaptainTurner", "3936170": "btd360", "3934010": "MalB_Productions", "3924099": "JJC090904", "3900573": "pierson-madrona", "3956860": "nutmeg8", "3901632": "akunzler", "3949412": "kiwiclevergirl", "3969112": "RandomAppleSoda04", "3956803": "cwktony363", "3995677": "idrisidris", "3948131": "georgewbush9", "3992311": "b00k_w0rm", "3996572": "TheSamoanThor", "3915573": "BigBadCheeseMan", "3922351": "jacobzar", "3938416": "88aa88aa", "3930132": "code-tvillinger", "3997752": "TRON100", "3947476": "tavinp21_lms", "3901809": "760573", "3958927": "manado", "3984897": "1ETHeR_", "3909227": "n1349", "3955840": "cwkjacob317", "3965885": "agdolls04", "3947322": "edgardune", "3942384": "Marci010", "3903096": "7891654", "3923365": "minecraftear", "3936020": "Meowmix300", "3918090": "micmuz", "3918088": "stasiech2002", "3984746": "FluffyCakes", "3922937": "scrath70", "3960329": "Sogdog", "3933955": "cwkfranklin305", "3902427": "laserrobot360", "3909591": "DaWaffleMan", "3937712": "SnowChester", "3961796": "123year", "3920123": "Kocoo", "3962418": "bwanaElliot", "3942191": "masio3", "3995058": "Katie1peace", "3961631": "TurtleAnonymous", "3927276": "XxStarClanxX", "3952248": "camster199", "3949121": "gnail", "3954467": "bramboman1", "3977412": "techclubmm", "3998193": "SpeedLimit", "3902300": "dragonclaw9000", "3958463": "PhysicsLover999", "3956004": "robotboy9", "3953001": "Kieran444", "3916238": "March14", "3925367": "cwkgrace262", "3924207": "Heatzor_101", "3956117": "Rainbine", "3954190": "schoolbythesea", "3949630": "GamerHipstah", "3989270": "SzAmmi", "3984490": "mrbossmanrules", "3956223": "-TheCosmos-", "3926484": "hadley2009", "3976693": "--Rick17--", "3921647": "tris104", "3933761": "Personal_Kiwi", "3912123": "jcaceres4051", "3911608": "xX_Holden", "3974666": "anime1011", "3903001": "martinh4i", "3995570": "l3g0_3nd3r_g4m3s", "3951064": "lilant305", "3964740": "schand4", "3941212": "-Toxic-", "3954120": "creeperboy0617", "3900352": "Simplyunexplainable", "3960289": "GJT04", "3961400": "duskpelt12345", "3921509": "firexspotteddestiny", "3927774": "FluffyMuffinz", "3966158": "dylan_33", "3901865": "Turboking", "3938493": "EatSomeCheese", "3951624": "zh18anth", "3954911": "pablito7", "3953971": "TwilightPonyRises", "3983238": "sir_fluff", "3903329": "bikingcat", "3991403": "lastbullets2", "3928746": "cooladmin", "3952905": "kitprojectexplorer", "3921165": "Alexcamostyle", "3969798": "TheEpicGamer0123", "3962153": "adasba2", "3998251": "firestar244", "3962640": "Skyguy278", "3994922": "pie_guy_55", "3930743": "iAmity", "3957005": "cwkgavin367", "3994795": "Scratch_Cat_7", "3933047": "cookieglue", "3968776": "Smartbones104", "3936508": "20tjcann", "3906284": "OpTicCocoa", "3983838": "xXBossOramaXx", "3906321": "TheDragonSk8er", "3956770": "TheStickGerman", "3939043": "garlicbreathinator", "3997303": "AquaGlow", "3999580": "Will_Warn", "3993502": "YourSecretAccount", "3944635": "follower23", "3992183": "Follower2", "3985593": "Gamco_Xtreme", "3948376": "ilovederanda", "3908710": "GelatinComedian", "3992680": "Black_Butler_16", "3986890": "3Diagonal", "3954762": "StickLaserScratch", "3968167": "Wompa101", "3946831": "MapandCompass", "3955609": "pokemon_2006", "3955973": "A-MintyThankYou", "3952697": "-EternalEssentia-", "3930150": "-Magixo-", "3926906": "T1TAN1UM", "3943390": "IFollowAll", "3936534": "-dat-axe-", "3921778": "-_Follow_master_-", "3929596": "UltimateFollower", "3927071": "FollowUser", "3924936": "MeFollow", "3918718": "The-Masked-Follower", "3918719": "fav_n_love", "3916066": "VirginiaShy", "3909390": "Follower58219", "3909381": "FollowAllScratchers", "3901948": "coolman-1", "3964463": "flealet", "3913746": "nookiepoop", "3954238": "legome109", "3952101": "jonerror42", "3960794": "jumphead", "3959829": "admiralwalter", "3949433": "Lily07", "3983470": "CrazySqueak", "3918850": "bits_and_pieces", "3955828": "awesomeplanet", "3938458": "soiledwalnut21", "3950576": "falconboy2006", "3933146": "nayeli12", "3998867": "vera130", "3936361": "OwlTennis", "3983316": "elsa6126", "3998700": "portalcreeper26", "3942334": "AquaticXerneas", "3909327": "aggyprincess", "3954865": "RabbitTZY", "3916185": "jsevy", "3995622": "Lucas10h", "3977650": "toadkid", "3990078": "TechWorld123", "3954155": "cwknevan352", "3985750": "analogclock", "3938789": "mat598", "3971545": "mfincham", "3976214": "zabdul1", "3905368": "dragons90", "3964239": "MinecraftFR", "3932569": "ROL520787", "3977587": "Volucris", "3944421": "newbos", "3907387": "estebanfer", "3933053": "jayhawk8", "3993148": "YoshiLuma", "3925316": "tacjakarta", "3956428": "nathanari", "3943846": "sausagehose", "3960552": "jt12013678", "3986249": "greenbird13", "3933695": "xXSkyrimXx101", "3933410": "wwqlcw2", "3998611": "Codingmistress", "3995853": "dvdcd", "3995379": "justbob7", "3942481": "CreativityGuy", "3953184": "warriorcatsrock4", "3957003": "cwkenrique366", "3933228": "jackwscratch", "3995618": "sundancing91", "3990126": "piggy03", "3966093": "orsomness", "3935255": "supercraft101", "3948559": "BRUINTHECAKECRAFTER", "3976782": "Dkid", "3916926": "soren667", "3971505": "etagg", "3951012": "TheHeroTeam", "3942638": "CorbanH", "3983418": "randomawesomeguy", "3924395": "hamilton36", "3915035": "cherryanggl", "3919087": "kumarica", "3977211": "yomama1ton", "3932307": "MOUNY", "3996116": "lionblaze50", "3955214": "jackoo4123", "3960874": "poopdork", "3988264": "c-dog_17", "3955361": "AstonVillaHUFC", "3992705": "MixxC", "3932391": "nimou", "3948779": "MyScratch2014", "3908390": "BrokenJayZX", "3938940": "Nasper", "3935801": "SirFurnace0ver9000", "3992021": "atomicprogrammer", "3983755": "cheesecurls123", "3908124": "pop32", "3917939": "NerbyParties_", "3909986": "jackshin", "3925131": "mcbrad921", "3922189": "sora18900", "3927152": "dywin", "3971536": "wdrake7", "3993517": "ViridianXV", "3968779": "minion1000", "3993119": "max-mine-craft", "3993575": "JJNetz123", "3947560": "_Umbreon_", "3972641": "g6bambam", "3954091": "Soccerhacker", "3954115": "tatooe", "3995558": "liverpool1everton0", "3948338": "enblazingfire", "3955596": "zacharyf2004", "3949959": "rits20100529", "3938604": "fluffy4287", "3975478": "Peeta1234", "3997118": "Louis1er", "3954449": "Godmier", "3977431": "Pixelcat14", "3916767": "scratchmanjohn", "3999056": "Scratcher72", "3938645": "Crystall", "3950021": "djamber", "3927267": "Super77dude", "3926408": "flutehamster", "3928493": "Creeper179", "3909369": "04dude", "3921104": "unknown225", "3927414": "9722225825", "3950279": "soccerrobot", "3981509": "gaoj5892", "3954139": "cwkben341", "3948859": "Stinkaling", "3993263": "The_Candlekeeper", "3911528": "warrior-cat-jedi", "3942720": "LZB2005", "3967500": "Funny_Stuffz", "3906586": "KeVDaBaws", "3923118": "noobydoob", "3961060": "bobkat10132", "3938265": "CookiWizzard", "3948587": "Jausterman", "3961452": "JuegOStrower", "3914406": "coolerik105", "3987686": "jhathaway", "3954813": "akirunrun", "3923532": "helbert167", "3943286": "4289", "3915958": "wolfking5", "3903470": "enderdog", "3954085": "shukla01", "3969232": "Hindianajones", "3939947": "jojjo_s", "3956372": "animationstar101", "3921704": "neonfirerider", "3912102": "poopster123", "3978410": "achang12", "3915630": "tigerlover8837", "3931148": "Invinceaman", "3954279": "googliebear326", "3979812": "WWThunderStar", "3981809": "vojtasonic2", "3921460": "ultradolphin", "3995816": "shrilaandvrinda", "3922111": "Trifreezefire", "3912835": "LJ06273", "3975161": "ik2006", "3995849": "brianna212scratch", "3908360": "Herobrine1_6", "3925984": "wykeham8_tv", "3983529": "minecraftpro16", "3946654": "lalala54321", "3995907": "cisconajera", "3998647": "dabunny", "3993590": "SilverDragon777", "3926815": "Yoshi64555", "3948050": "21lillyde", "3946584": "angeliclayer", "3943521": "wolfloverkiddo", "3955620": "mikeono1O2", "3984451": "cwkconnor376", "3968989": "hyena9", "3920174": "SnickersThief", "3909399": "MeMyselfAndScratch", "3932526": "STR542770", "3981363": "jcooley25", "3996838": "BE_YOUrself", "3952444": "ashwinr_test", "3998571": "wookie184", "3996340": "rockymountainboy", "3944007": "kidman92", "3956402": "LuVi", "3955659": "PHONECAT", "3956802": "cwksam362", "3953979": "AOS_studios", "3927775": "NaNoWriter", "3995723": "AnimationTeam", "3994200": "Eddy360", "3900114": "Omigrantis", "3936764": "224615", "3903039": "usedthenwc", "3955992": "Andrew1260", "3935136": "Scratch_Blocks", "3969785": "leiadog", "3993972": "scratchieHD", "3933927": "cwkalex285", "3992813": "Frozenlover456", "3933964": "cwksophia311", "3937989": "Xander52", "3908906": "epicam", "3926446": "cookies8", "3999551": "Adventurer_X", "3997313": "mrwuid", "3943112": "judes21_lms", "3924016": "Zvizero06", "3962941": "stealth777", "3914551": "d25zachary0189", "3907847": "EvotheFrench", "3938258": "ninjadude698", "3919733": "themoona", "3961540": "-TotallyEpic-", "3953727": "xercus", "3955673": "ghoststickman", "3909149": "Ermagerd117", "3938682": "billywilk", "3977608": "JesusFreak18", "3933942": "cwknate294", "3998831": "CEH1", "3972157": "SuperDoom", "3990878": "-TheUnknown-", "3915600": "Ridicolas", "3948656": "lolman67", "3926439": "herbsts", "3927794": "PHAROAHKITTY111", "3961354": "droidmann", "3904198": "worldmaker", "3961586": "bobforgames2", "3966805": "PhantomSlayer", "3902603": "pikakitty300", "3953889": "ImperialGames", "3985532": "zelda543", "3982882": "maffe03", "3943990": "Gloo", "3958320": "DiamondFever", "3901767": "catscratchfever101", "3924431": "mrzap6077", "3953752": "TheGoldenGamer123", "3993335": "ChocolateCupcakez", "3908171": "rad534076", "3939401": "pinkielight", "3939485": "Teger", "3952083": "sharkysmile", "3992105": "BookyWook", "3954870": "Supportarble8", "3993231": "KatnissfroyoQueen", "3949080": "gamewizardkid", "3954007": "DTkid67", "3924776": "ButterElf156", "3922602": "BlauZwerg", "3959676": "Yeti887", "3900253": "vegac1097", "3985815": "Silverpaw4444", "3985877": "programmermin", "3985630": "PhoenixGames", "3946029": "Gmgmario", "3948992": "ZAZAKID13", "3920756": "PoisonEye", "3993555": "ckpm", "3901534": "Pixel-Master1", "3996312": "chocolate-stuffys", "3933727": "Kayne256", "3908638": "winggar", "3915991": "LikeABossTV", "3995965": "RiotBoy12", "3944491": "Epicscratch4432", "3981013": "kannin", "3968614": "dovi18", "3923848": "bigfootlover3342", "3929813": "fasd47", "3985769": "garbij", "3969547": "NinjaJ108", "3998122": "Spyion", "3985035": "hihokermit99", "3998198": "applesnap232", "3942491": "coolman300", "3956441": "megabeth15", "3962090": "KittenCoder5700", "3992743": "videogamer1002", "3908188": "Just_A_Dream", "3916109": "HeyYa11d7", "3994425": "Hobson-TV", "3980832": "Manofwax", "3995109": "superdude9997", "3984472": "Quayl", "3964715": "tshanm1", "3921093": "Nova_Turbo", "3923182": "Meganova", "3993094": "LessBetter", "3986914": "finchYT7", "3932492": "FluffyOwl123LOL", "3914453": "RYDERABOSS", "3953788": "TheGrimReaper200", "3925356": "cottonbloom", "3924147": "FollowNation", "3962832": "zmcclure", "3962075": "Brainz", "3905309": "youngmi2022", "3950961": "plasmic_titanium", "3969050": "TheMuskateer", "3968597": "Jell-man-123", "3959815": "Aquaflame", "3935963": "TheArtFreak", "3924662": "Spawle", "3900228": "rainbowdash1660", "3916401": "puffleparty", "3923893": "xOnic", "3954580": "iceclaw101", "3952513": "JooDee", "3917611": "perryiscool123", "3969640": "hparr10", "3962140": "Superscratch804", "3969368": "fairhopekid", "3972366": "Abri44", "3900065": "K-Productions", "3923919": "monoo", "3998844": "RayGuy", "3931216": "chickenking_1", "3916607": "chibun", "3931200": "darckenter", "3997903": "Girlybrine", "3954248": "_youtubeN1", "3900866": "Awesomeman30333333", "3926693": "CrimsonChaos", "3945386": "Pingaleon", "3966444": "survivialcraft", "3902425": "yarn123", "3997379": "KOstek123", "3993106": "db200046", "3924847": "GraceTheFox", "3954693": "pjnair", "3985927": "kadhat", "3908113": "peace227", "3942206": "NoBa00851", "3933655": "Spottedleaf13", "3939750": "hedgey72", "3942916": "The3dMaker", "3942455": "tacoboy", "3956010": "awsomegamer2000", "3940917": "RGBD", "3976106": "brutus111", "3918675": "xxfirehivexx", "3943276": "DerpSsundee", "3957120": "diamondsworddoesmc", "3976244": "mysteryboxlover", "3914420": "greatberen1", "3916212": "gamerboy1310", "3940554": "antineutrino-", "3994774": "andreazavaglia", "3965042": "californyaa", "3912528": "MarfMaster", "3951437": "nicopro", "3931776": "Camembertm", "3939320": "Codeplayer", "3912530": "lpescalebc", "3985139": "ColdSpike", "3932190": "Turtle_King", "3968215": "Tiptopcouger6", "3916631": "Bball1204", "3924040": "nonnino", "3961859": "edward789121", "3931846": "afropig", "3937721": "gamer079", "3980234": "Elementex", "3952714": "CaptainAnime", "3938253": "love_rainbows", "3977544": "Zeno-Star", "3955353": "liddle_conquerer", "3911785": "Complicitmoney2", "3936681": "DiamondFTW", "3958952": "Mad_alchemist", "3967837": "Your_Dog", "3932788": "dman07", "3953477": "guesswho111", "3913365": "Procrasti-nation", "3958634": "s2078437", "3967859": "cb14985930", "3961504": "laurenlover", "3954611": "2130055", "3922852": "MWA1128", "3989050": "Sebastain_", "3951637": "bh18neiv", "3993273": "epicman3354", "3943599": "Organique", "3938371": "CodingCow", "3960843": "guiles", "3998241": "happyLOL116", "3934793": "HenriGamer2", "3924022": "ElImpresionante", "3956196": "coolness_squared", "3998462": "Pawtiko", "3925139": "bushyeyebrows56", "3990381": "flamehawk13", "3901867": "shoxypikachu", "3979072": "Kapanyo", "3977769": "kamikaze_onion", "3966870": "Demondude12", "3931879": "faygone", "3915979": "SpinningStarfish", "3936658": "Catsith", "3946123": "SeaRider", "3932945": "anthonynes", "3960051": "Jam302", "3985910": "Mikaru", "3920752": "meg_boe", "3952320": "partytime12", "3962086": "Angie20032", "3960287": "LoreRedfox", "3925576": "monkeymane999", "3999313": "evolved-sky", "3995733": "Headphonez", "3906624": "Greenforce", "3927507": "lightningboy135", "3924934": "SkyMargo", "3924243": "rainbowzandlol", "3953450": "dragon_bros", "3995435": "origamiduck", "3968867": "dogcake99999", "3985344": "mcubed2", "3904501": "SrslyTrapp3d", "3942549": "Pixiegamer_Follows", "3993134": "racgreen", "3985967": "Miracledun123", "3918892": "anthonyallen", "3914447": "redninjanathan", "3990936": "SkyBlue_", "3995653": "AnAncientTale", "3993131": "new_free_life", "3909421": "mrchickenman2003", "3952155": "SUD2001", "3933504": "SapphFyre", "3923769": "Vectan", "3951140": "Leroy_diamondblock", "3948270": "fluffii-fox", "3950015": "fonzereli", "3955279": "rainbowrocks", "3907632": "epicRedHot", "3993057": "death_bringer5", "3997822": "GamerGirl55", "3916488": "sammyjoon", "3957853": "Jordon02", "3955521": "-EpicGuy-", "3925185": "MasterOfArithmetic", "3999390": "MattBen789", "3944411": "kinisbe", "3906516": "Darkend", "3975163": "Reaper2000", "3979066": "malikdahra", "3954664": "paddyman03", "3989235": "nalgaman234", "3908962": "epikplay3r678", "3996648": "BossOfTheBosses", "3946439": "sniper9090", "3951809": "vvvvWafflezvvvv", "3987685": "sulaiman987arif", "3927082": "Kidplayer111", "3992142": "GravityFallsGurl", "3975501": "epicninja2002", "3982937": "DestructoBot3000", "3977746": "shadow_pro", "3961200": "RJ_12", "3993518": "tinytimmy", "3956712": "epicraichu123", "3997857": "Cheezburger101", "3996846": "A_Murderer", "3996687": "BrainBolt", "3995843": "BrightBolt", "3994423": "Gamingterra", "3950335": "tucnakzuval", "3956256": "ConsoleBlue", "3974649": "_Scratch_Dragon_", "3909567": "taytay4321", "3993389": "WafflesOnDrugs", "3968800": "jea719", "3992931": "GrahamStudios", "3992668": "Following_You", "3984978": "kittylover677", "3908450": "KingofMiddle-Earth", "3909055": "GoldeScratcher", "3988303": "TYRONMAN111", "3977641": "InterCellular", "3955683": "neonpinkllama", "3985398": "-TheUser-", "3983017": "vernman23", "3938983": "Jmec", "3955972": "Cookieating", "3932285": "esha999", "3939124": "SuperProgrammerPlus", "3967262": "CorndogUniverse", "3946154": "cbussard", "3971605": "BGDood_Tutorials", "3969524": "OnceRight", "3968974": "Dark_Matter", "3968512": "-Ortiz-", "3953649": "_ExplodingTNT_", "3967069": "bluefox102", "3959608": "JuliaB00lia", "3964394": "ThePro-121", "3961336": "Spikers", "3957969": "SamuraiLime", "3936075": "Gadget_Girl", "3940406": "elephantcrazy0", "3955546": "Twoheadbanana", "3945517": "Ecilptic_Inc", "3931279": "23sarsar23", "3955142": "ThePro121", "3955420": "srglenn", "3925044": "griffpatchhelper", "3953983": "MirixStudio", "3953977": "BVADDIE", "3947749": "game_heaven", "3904210": "blockbluster", "3952481": "einstein23456", "3952401": "GPS_Follower", "3952337": "Banana_Inc", "3951514": "AerialForcer", "3951047": "victof", "3950349": "Sun_Ray", "3949270": "WolfLover678", "3948874": "MinnieMouse123456", "3902182": "-theone-", "3948580": "Marvelfan1", "3947667": "HelloKitty500", "3933792": "puns", "3945373": "gamer_3000", "3938862": "raptoron", "3940498": "thatKitten-MDL", "3943313": "rishabhdoesscratch", "3939728": "TheUnicornPrincess9", "3936948": "PureBlue", "3941012": "-aqua-", "3911733": "Perpterts137", "3932062": "gummybear678", "3932979": "KittyKat345", "3938953": "Boy_Lover_123", "3931121": "yveltalEX101", "3924658": "Pokemonfan13", "3935833": "VectorInfection", "3928293": "Awesomekitty1", "3921680": "morning-star", "3927987": "sartoj", "3921316": "catfood3", "3925987": "Hydrogemeni", "3923215": "PeteCom", "3925047": "WickedChips", "3924148": "MinerBlaze", "3923500": "Anne_7", "3922084": "Brendan543", "3907548": "Tixx", "3907772": "Circumference", "3914748": "Inmate_64", "3913681": "FollowKing", "3909014": "Anime_1", "3908807": "EpicScratcher25", "3908408": "-TheStalker-", "3902567": "isabella12478799", "3904902": "blitzflare017", "3993583": "husaco", "3945720": "rits20100406", "3922591": "sachi218", "3963509": "miopenguin", "3968829": "sitaracool01", "3958022": "redcandycane1231", "3956963": "OAKAS", "3950111": "June_Johns", "3951510": "rexor1", "3946991": "rhinokai", "3965062": "Rainbow_Unicorn101", "3935303": "OOHH", "3924131": "mash417", "3921894": "you99ki", "3945712": "rits20100367", "3952834": "rits20101096", "3943035": "lesterdylt", "3956482": "rjsaurus", "3915501": "kappahime", "3985939": "laughy123", "3932946": "seph11", "3945737": "rits20100749", "3999224": "FBFan5000isback", "3997777": "skip_wishbone", "3995602": "BiancaDiAngelo101", "3996799": "YourTestAccount", "3916988": "0987654321123", "3930358": "JacobyJr", "3904274": "mansua1", "3998020": "vooders", "3948118": "JumpingRabbits", "3987392": "catsoft", "3929763": "Darrell_Rivers", "3905989": "SummerPoniez", "3913312": "BeastMode510", "3955347": "follower5000", "3914131": "cls01", "3930695": "bilbo55", "3954307": "Asjali", "3996597": "randomcoolface001", "3975081": "stewiecrazy", "3989382": "theepicpreson", "3984793": "sokrat115", "3946854": "39585", "3906588": "EssyK", "3982784": "BarbaricHoodie", "3930329": "faiza9", "3914869": "scratchfan1805", "3934427": "SuperscratcherXD", "3977203": "LavenderTowncat1234", "3961658": "A_N_I_M_E", "3917038": "DomTheSquire", "3907173": "pmcgaughey-hrs", "3907253": "SpacePets2004", "3949659": "PelangiBulanPurnama", "3944506": "Midevalknight103", "3916276": "Oceanshimmer", "3953731": "phbug", "3933941": "cwkkai293", "3943933": "MarioFanGB13", "3961217": "singer44", "3955867": "happy2288", "3998899": "AgentBob", "3921761": "QuillandParchment", "3967276": "Gaboo8", "3954266": "Loganmonkey", "3921406": "HazelTheCat", "3991432": "xBayani", "3944647": "woaow", "3901144": "silvaedw000", "3952673": "moontheanimator", "3916515": "tigergong", "3956868": "carrotbaxter10", "3955446": "elsapower", "3926921": "NoMoG1", "3925433": "jennycaro70", "3961558": "ferzo1237", "3950192": "kitkatcrew", "3988451": "AAK111", "3901834": "NickF5", "3978668": "Convexity", "3931869": "everything_books_", "3919602": "user0214", "3923198": "Dankuk", "3926037": "BaddyPouFan", "3995928": "gilbertcollins", "3966900": "NaomiLuvsU", "3923608": "gaelle_121", "3948186": "Pink_Pluage123", "3943028": "Birds_Red_Info", "3939441": "ATraX", "3967427": "swaglifeman", "3927157": "--Phoebe--", "3955449": "vbbvbbe", "3946752": "thomasization", "3936686": "Bekay90", "3902643": "Esha99", "3932786": "jordanlebronKD", "3946587": "ladyjam123", "3952042": "FollowAllThePeople", "3925497": "yukit215", "3934855": "ryuusinn", "3925925": "nyaonyao"}