{"4154000": "marony", "4159171": "shunart", "4141600": "Obamagirl", "4161270": "yosi2002", "4161665": "sussikitigai8", "4150272": "tomoneko", "4150347": "Galvatron110", "4157862": "AnaMat", "4120497": "furki123", "4156968": "cbuster", "4158011": "Porkchop23", "4156231": "RoboAsterix", "4193498": "Ishark98", "4177968": "jclutch", "4195741": "ScratchtheScratcher", "4159080": "Loudleaf", "4153883": "Bemo111", "4149226": "ILoveGerbils25", "4107455": "ninjp", "4156974": "zedOFF", "4167405": "for539", "4141430": "cre8er", "4158218": "Slywizard", "4164160": "PenguinScratch123", "4198326": "IsaacAndBrooklynn", "4158348": "geronimo10", "4149935": "s201201121", "4158738": "Fennekin01", "4173774": "Rubysnake", "4178943": "CaptainCreator", "4151326": "X-Blazer", "4118736": "Puppy820", "4196741": "endermenarecool", "4145832": "millagez2024", "4178065": "G_and_K", "4158498": "AxOdin", "4168187": "Sadie001", "4142295": "cinos123", "4186040": "bigflower345", "4172729": "scarletpizza21", "4134944": "Mortalist", "4168941": "Rascador", "4149338": "RichardStarbright", "4197618": "ale359", "4178182": "theunknown756", "4140703": "Nightjay99", "4165284": "Aceofbass", "4148172": "trexvoogd", "4165688": "gorkemyapimcilik", "4108721": "longwind", "4148904": "LittleMilo", "4187939": "osem2", "4187091": "Chacko10", "4156173": "ohmnom3", "4110903": "Ellasa", "4164804": "QUEST6", "4117988": "willjosbudgmail", "4151540": "NeonTech", "4168104": "ssuthar", "4195445": "-ScratchOn-", "4185538": "MICPICSCOM", "4154035": "Grash", "4153153": "_Legolas_", "4153876": "coolguy989", "4187877": "sharkboy05", "4149894": "minecraftchris123", "4136332": "flyingblue", "4187741": "-ToasterTan-", "4148423": "Thinkmachine", "4163057": "songjun2001", "4112938": "-TheLizard", "4105071": "Fanta2003", "4146532": "Lavendershine", "4155955": "mobear", "4192580": "trolldance", "4109123": "GrayClouds", "4132106": "olek128", "4123758": "AquaCrystalGames", "4172225": "FrancisAlmeida", "4128392": "Mit_educhick", "4196846": "lego200504", "4193347": "_Endercat_", "4194731": "Keywave", "4175253": "scratchswag99", "4122682": "5ellinic", "4158968": "MANDOG-69", "4147374": "buildofawesomeness", "4177712": "awesomeshadowclaw12", "4153206": "Cymphonia", "4192464": "sabi2992", "4140547": "Toast_is_AWESOME", "4167736": "baby25870", "4129067": "dorrty_design", "4127485": "danthescratcher", "4199748": "Ieevee4", "4187645": "Xith", "4184370": "Follower101", "4157877": "Vectle3", "4136284": "JTvideos", "4157365": "legochicken", "4140475": "true_13", "4129342": "DaFollower", "4105406": "YoshiLightning", "4143137": "Thezjx", "4195665": "opaline", "4184366": "alanz7", "4117837": "ebora", "4178265": "Thebeast972564", "4154075": "Leg0dude13", "4198800": "amazing_amir", "4175110": "thebros2", "4151280": "wyatt64", "4177028": "28spongebob28", "4114099": "ZombiesRFun666", "4158001": "nikhildns", "4154151": "mets2007", "4110661": "yankees2004", "4192197": "honecy1", "4156168": "Rabbidscant", "4197231": "Leopardpaw3", "4149237": "elovee", "4118351": "MK_Learner", "4198076": "AnjaNC", "4109134": "gerwin2018", "4106383": "fishface1st", "4126827": "assasin_ww", "4179694": "Codingmaster1", "4139149": "hartmara2025", "4176022": "overlord202", "4145143": "lonl12", "4187017": "mrzbell", "4152820": "knightsadventure", "4148997": "supermosquid", "4198221": "goombie20", "4179683": "looptheloop", "4195562": "Arcticbrady", "4105065": "marco61554", "4189014": "zooki", "4154295": "ayushmish", "4198688": "JacobSmith3204", "4153429": "8017", "4102009": "360-110", "4167595": "GermaphobicCoder", "4181365": "Carterboy11", "4196824": "fail_selfie", "4163012": "Rainbowycat", "4195783": "sonnythesky", "4161056": "kig345", "4167731": "spearstroker", "4108325": "Japadog3000", "4184195": "mihenderson", "4141585": "sfo123", "4129568": "Munching_Orange0_0", "4167125": "BoomBoomPow2", "4103217": "CunningBaldrick", "4105849": "ssi_de", "4132291": "bambam2", "4132359": "Sapphireboy21", "4109016": "yummy_cookies", "4149553": "Melthecoolcat", "4173172": "ippolitima", "4152860": "pencil90", "4167267": "ismaha9", "4122487": "VilleTiger", "4126337": "ConV2014", "4158572": "Princesstigerlilli", "4187436": "4655925", "4187804": "pipster28", "4167636": "alexman7", "4128996": "lucasv123", "4197763": "thesecondbaron", "4193511": "mextie", "4128227": "FBDagar", "4167375": "francofantino", "4153906": "mooshy_loo", "4104881": "cristiano8748", "4121396": "aalto", "4171390": "Hirotan", "4107014": "aKorte", "4151880": "trouble72", "4142484": "patafiks", "4177859": "tena360", "4151890": "DragonDare2", "4191827": "mancity2012-14", "4150577": "williaug", "4140848": "fafa18", "4129619": "TheFunnyDude", "4187472": "xTheGreatTurtlex", "4126121": "CatnipEverdeen1", "4154681": "jojowillow2005", "4142067": "NINJAX_", "4129770": "Loggy1", "4117013": "tom_bomb39", "4168522": "sk8723", "4199396": "sailwithfungie", "4102906": "XX-gta5-XX", "4149407": "OrvilleTennis", "4164116": "Bsned", "4153048": "froakie123", "4108167": "corevolt", "4113710": "TheMisterG", "4156118": "1sesu1", "4194210": "CinderBerry1712", "4116190": "BORG_MAN_16", "4140615": "Owllover8805", "4128173": "dev6785", "4197705": "TehConMan", "4167715": "randomlozvids1144", "4117775": "smalleystudent26", "4149754": "crushingcrew600", "4137586": "catmat52", "4105444": "jnmkl1", "4103814": "MB3610", "4177199": "s-wford", "4118479": "lexilulu352", "4185343": "DualBios", "4152216": "snickerdoodleJTW", "4193452": "tombessford", "4107400": "WarrenBatman", "4185524": "dantdm3", "4126616": "koestedi2022", "4156046": "Jponah", "4198833": "Levi35241", "4153396": "Jellybean_Queen", "4196003": "GhastlyConjurer", "4153893": "Techy2000", "4124504": "Purple_Power", "4127328": "calalzo", "4187558": "epicturtle15", "4149889": "jtsdenver", "4103842": "AIM725", "4133367": "turkeytom", "4130201": "sebtom", "4118622": "blue807ndy", "4197004": "bandicoot2003", "4144960": "metpps", "4104871": "atvrider987", "4127008": "Xawesome", "4124582": "the__ninja", "4115113": "dalekboss", "4163818": "draxalone", "4179631": "pabury", "4118255": "PokeTheMinion", "4182096": "kuesuto", "4144565": "the_bee", "4159011": "maxymarcus", "4155570": "jadegreen11", "4154963": "douggy", "4183646": "nh23wqa", "4187080": "chiara_ani", "4102492": "TL789", "4152836": "as112004", "4126641": "judydiepie", "4105650": "aarongibson", "4142073": "atortello", "4142994": "OMGGamemaster", "4181878": "coopershows", "4188110": "HSL2014", "4168535": "Nicko04", "4197040": "coder778", "4159061": "onerune", "4188503": "jarjar190", "4108253": "smalleystudentms", "4141412": "BecketThor", "4152917": "EpicChicken", "4162210": "maximum42", "4176254": "pheonixfeather45", "4109680": "18eld", "4155443": "eleips", "4187608": "FollowThousands", "4154241": "gameboy4", "4197221": "Lukluk81", "4118970": "Zbair457", "4196984": "shadowfan0", "4193107": "GANGBANG234", "4152975": "AmbeyBambi", "4161108": "Alpha_Bet", "4120143": "Deadpool3980", "4198158": "Noahofbass", "4151695": "coolkid1222222335", "4125488": "barryscott", "4188347": "Pixelsmith", "4191281": "geegee6", "4186670": "mwendwa123", "4149411": "2005buster", "4188123": "WiggleKitten", "4117768": "four-two-nine", "4111353": "packif", "4125210": "NixyNoxy", "4158138": "script8man", "4113240": "ATAT123", "4151363": "ThinkerTank", "4135129": "warlord5", "4199379": "SuperMrGobo", "4100896": "CatsUnited", "4133500": "JoeBoy5", "4147455": "PinkPrincess12", "4118042": "mats08", "4100772": "lennystef", "4125619": "nielsk", "4138304": "ek10", "4184340": "redrihno", "4176363": "Girly-of-awesome", "4106001": "xDubstepxMurdererx", "4159827": "Coolcreator101", "4174635": "poseidis", "4116944": "Catwoman05", "4178417": "turtlefriend2", "4119358": "awesome5185", "4100281": "MrYan900", "4183748": "McGraw", "4154495": "alviny01", "4177943": "bonesbrigade123", "4178536": "sealilly24", "4104889": "Mudforce", "4188109": "ImpioDementus", "4175548": "LightingGod", "4177806": "Flain2464", "4150446": "Sasasain", "4184940": "Shaferman", "4193503": "4ever_llama", "4163102": "MsTeee", "4129473": "Foreststar204", "4190323": "danny23445", "4119831": "milesaway123", "4129160": "buggy680", "4194810": "161570", "4156133": "Miner520", "4175893": "Mexican_Kid13", "4141530": "Reminstein", "4195903": "FireMarauder", "4140553": "thearchaeologist", "4157587": "max_and_zeke234", "4125551": "EThanMarty", "4155652": "ComicWorldBros", "4175966": "sealfisch", "4118163": "theman3446", "4134940": "Oddysseus", "4153569": "Everto", "4104283": "Z-patch", "4180951": "SNUGGET", "4145694": "tiffanyspurgeon", "4118203": "hello4423", "4130344": "-MagicMan-", "4179516": "oshobreaker", "4171936": "Snivy2014", "4108358": "LeeegaaaCy", "4129074": "StumpyGecko", "4104691": "NuclearScorpion3", "4140953": "plamjo", "4112660": "CraiziFeed", "4199242": "IReko", "4194837": "ShadowSpear123", "4173750": "jigsaw45", "4187403": "ScratchBoss2004", "4187223": "Little0cd", "4172842": "packersp", "4195171": "Gtest-", "4179337": "ZWain24", "4193874": "tigerlover2468", "4182344": "Azza2300", "4155954": "-connected-", "4187345": "CaptainCarrot", "4108626": "Ackoli12-", "4155684": "apakk10", "4186957": "MeFollowYou", "4185996": "NRH2", "4184320": "Nepon-Grizon", "4185498": "Now-Everybody", "4178776": "LavenderTownFanCat", "4183236": "MoneyManrRage", "4105506": "MissPriss13", "4182354": "TGIF_2014", "4144158": "fragmanialains", "4177583": "Dr_Uranus", "4174598": "Olivier-Li", "4140985": "esarge", "4152313": "raxer", "4128785": "legolord999", "4153032": "murse", "4152761": "LoLmAn_007", "4152630": "BaconNinjaGames", "4159429": "DiamondRock", "4148218": "fd45", "4140973": "Bad_Mushroom", "4159075": "TheMusicChannel", "4140913": "Bijuu", "4149266": "GamesForAges3-100", "4158514": "sanian", "4155768": "Artemis_Fowl_Jr", "4155844": "MMHMMH_test", "4155487": "Josh_k", "4152626": "IllusionsGirl", "4140716": "Duke_Of_Weselton", "4153522": "SCRATCH-AWARDS", "4129172": "Elindil", "4152127": "rnath2002", "4146030": "-NightSparrow-", "4118728": "dman2006", "4149307": "Arctos", "4118409": "Idiontguy", "4149586": "jonmitter", "4141558": "EnGeneer", "4135943": "123AVI", "4133613": "LyrBaby", "4123833": "D3nnStudios", "4133436": "dante79", "4140463": "Advertiser9000", "4140255": "Free_Follows", "4131814": "mrdp", "4120630": "kchin999", "4126434": "Paradoxal", "4129437": "BTTests", "4107493": "TheDiamondPick", "4116660": "JoBro88", "4115550": "trollmad3", "4121876": "Ninjaboss123", "4119647": "Maranatha1225", "4107371": "shadowrogue752", "4118437": "PleaseFollow", "4117905": "RockStarAngel", "4106294": "The_Slasher", "4108125": "TheIceCreamCraver", "4107429": "yyyyy14", "4141212": "6212151", "4147319": "ferrerma2025", "4178337": "The_Scratch_Squad", "4193651": "ScratchyDrawing", "4188188": "NSDNSD", "4121622": "suzie-", "4178880": "diane12", "4149187": "siguenza", "4176255": "sabeehakhadeeja", "4102088": "shun_take", "4199448": "oligami", "4130150": "Sigemaru", "4178979": "abihazi", "4155237": "BlackAndWhite007", "4154356": "amijako", "4152254": "SSSFollower", "4150964": "Storm_Elsa", "4128595": "Jakencutt55sFollows", "4186920": "itchymanmaker", "4143686": "CandyJery", "4152208": "Ananda90", "4145051": "08inam", "4152946": "OwenMacPC", "4104169": "oliviakitty9", "4147931": "williahe", "4112652": "ScratchWaffle", "4129481": "manyapbhat", "4129142": "nmitter", "4148857": "PigeonsEverywhere", "4122372": "ScratchHyperspace", "4119410": "FawnRider", "4168561": "123clint", "4151300": "The_Inductor", "4149956": "LunaInWonderland", "4119651": "SmileySun12", "4108426": "TR_STUDIOS", "4178266": "Richierich123", "4173756": "corrieadea", "4140665": "The-Sonic-Fan", "4168357": "artbunny-", "4151211": "dawoodmtan", "4188360": "Mammiso", "4142115": "HORSELOVERELLEN", "4157880": "Katniss_and_Gale", "4152324": "abclop99", "4169057": "stormchaser12", "4114536": "Pinkersgames", "4153619": "Teedz"}