{"7459212": "depolary555", "7465792": "Or1gin", "7479052": "CoCoBotan", "7470116": "ystyle", "7465768": "nshah3", "7466456": "Cushty-Creations", "7402406": "AwesomePizzaDude", "7467340": "motorcycle2000", "7481434": "pneuman", "7461440": "22erikals", "7494762": "sparkle24370", "7475978": "MrPotato2007", "7461146": "DewMcStew", "7470626": "30kg", "7481070": "nitrous33", "7464928": "GonOliver", "7457720": "swordrider", "7426642": "rittachoi", "7461348": "TheGamingStar", "7455372": "Duckyface", "7403692": "Arthur_007", "7482142": "UnhackablePlayer", "7461668": "_OinkyPigs_", "7424298": "TaylorSwiftDinosaur", "7496200": "BUTTERBATH", "7412634": "4mathman", "7412522": "Fruitbatty", "7465782": "thebman1", "7465924": "Pythagorm", "7438820": "sprince47", "7478358": "Neon_Warrior2", "7472878": "venusp", "7417214": "ZurpHead", "7499964": "LMbananaman", "7458970": "Stampydan13", "7480320": "scratch_catch", "7478938": "agp2003", "7465130": "Scribblez2003", "7487338": "SirConrad", "7466950": "newmcq", "7419054": "Maskette", "7441406": "The_Master_of_you", "7462336": "yopiedude", "7462366": "Tilkii", "7416264": "carfly", "7460960": "007Troll", "7412872": "990000274", "7456304": "Tech_Dropchord", "7457484": "InfernoGhost", "7400988": "scratch-o-matic2", "7455840": "9-plus-10", "7431388": "henryrises", "7428054": "ZekeAndZander", "7495430": "Davinci1123", "7430562": "moxietea", "7415004": "booshy19", "7427776": "Ajpuff5", "7455806": "firebird87", "7477740": "SilverKitten101", "7487912": "Darkspike03", "7475766": "coolmanol", "7460836": "siriusexpert", "7494058": "Scratcheristic", "7424810": "Eggmanjames", "7466854": "brighton314", "7455400": "scravvler", "7462636": "Darthvengeance", "7492072": "empire1", "7444794": "sirfused", "7410884": "frown", "7445278": "wolfblood123456", "7476224": "RatLover9", "7402762": "cwktrue1984", "7413150": "abox", "7402722": "cwkkenzie1982", "7468116": "RainbowDashBot", "7429724": "Gigno", "7456000": "sparklechu169", "7404078": "narfi9", "7461182": "JakobHTV7", "7461194": "LisaHTV7", "7430570": "AshBreez450", "7417352": "sam8spy", "7477018": "piemansofia", "7430878": "Moosehax", "7414990": "shulern", "7429510": "pokemon37021", "7475814": "Floperatox", "7467870": "cutepower1", "7430340": "519NEAs40", "7466890": "mangagirl2004", "7489488": "lc23515", "7498272": "tks755", "7468300": "jmartin15", "7415868": "Wizard_Games", "7403322": "519LEHa30", "7400252": "qzh30d", "7412112": "artsamq300", "7437422": "Xx_Best_Gamez", "7456650": "RootJ", "7402950": "Mittenpepsi", "7446488": "Ryanj23383", "7462570": "LilyPhan", "7427962": "cooldude27378", "7427822": "carrot-cake", "7459820": "Erin_the_bunny", "7400504": "Vampire94937", "7453218": "fireball19", "7474050": "bitsbits", "7468040": "vulfy", "7476058": "Gun_Boy", "7443888": "derpyassasin999", "7406798": "Riaz101", "7498004": "2015_Gwen_Nerdy", "7400850": "TheMarioDude", "7417120": "TylBrad", "7400334": "74581", "7456742": "rexwaterbe3", "7430132": "519GUAr40", "7467886": "kitten927", "7453804": "cookiemonster1853", "7456748": "MrRionShaggy", "7460158": "Scratchy-Scratcher1", "7448430": "Haribo05", "7473622": "FrostFur458", "7410308": "megarow", "7456154": "Budderjohn", "7467018": "cwkmehul2000", "7471834": "jcl32", "7464534": "legendaryxxx", "7471798": "rcobbsg", "7459430": "Fishleigh", "7414450": "thegigabrain", "7468048": "FoxyandChica3055", "7429688": "meeee10", "7469298": "Planet-Earth-2", "7465434": "Hikabee", "7497158": "michael-jacksonfan", "7495892": "Maffthekid", "7465696": "BlondPaladin", "7464602": "greenpesto", "7444398": "remixer-man", "7477798": "Jorosan7", "7472070": "P3NGU1N5", "7478022": "Goldenblazethecat", "7401090": "TheMiner56", "7429722": "WAFFL3", "7474176": "Medley7", "7475262": "ILuvNintendo", "7412030": "iAmGroot235", "7463854": "91084579", "7421492": "supa_awesome", "7418358": "felog", "7450750": "OliviaBubbles2005", "7477748": "PixelMation", "7446418": "htyggg", "7436930": "BabyGurl1992", "7426540": "Nightshadow440", "7413600": "cjs_ahemsley", "7428152": "IzzyGWC2015", "7473152": "Koloa", "7445236": "mishyfishy-_-", "7426314": "wikipedi0x0d0", "7485444": "pheonix_1", "7454416": "NR26", "7477860": "EthanCW", "7499378": "codemaster118", "7428968": "Leena2015", "7402488": "YellowRiver54", "7462816": "21blodgettm", "7441374": "awesome_popcorn", "7441588": "Fennekyn", "7411994": "SousVideBrie03", "7411988": "hellokitty5000", "7447010": "408040", "7414904": "Im_a_Fish", "7411870": "dabigcheese1", "7437332": "Justin1940187", "7417148": "scrondun", "7412078": "JK340", "7473208": "E-cool_creator", "7411976": "bluebunny2835", "7450578": "325245", "7411902": "bobthesnail0", "7411978": "epicgamer555", "7411892": "sparklypants", "7479066": "psyduck1", "7454614": "lunarpelt", "7466680": "gymnastics535", "7474978": "bamboo7", "7416912": "ghastlyghost314", "7453486": "yashamax", "7446820": "PandaGirl91014", "7411928": "Bobthemonkey1", "7442396": "LM-65820", "7411886": "neonsuperninja", "7479608": "Hikarunia3", "7463286": "amelkamala123", "7465664": "Theresa2305", "7444870": "El_Matador_BTS", "7422200": "siebr001", "7415332": "HuMid74", "7488232": "14788", "7478764": "-Account-", "7419254": "arcticmonkeys701", "7456086": "thecatch2004", "7491420": "MLG_x_shrek", "7413742": "Gage-M", "7401828": "P3LIVENOW", "7477240": "_Yellowshine_", "7496214": "nich1001", "7413430": "MrPenguin35230", "7470072": "loladragonfire", "7452438": "Sharkicorn321", "7466032": "redjumpysnake", "7439950": "Ttugf", "7498276": "DeluxeDuckBenjaminH", "7487154": "TheoryofaDeadpool", "7483744": "_Rick__Astley_", "7426922": "hunter310", "7454006": "Blue_dolphin_5376", "7456572": "carguyz", "7478226": "Mangle_the_pirate", "7488978": "linkinparkloon", "7430012": "-Carbon-", "7423004": "olmorea", "7469306": "pusheenkittens", "7483952": "LittleBunnyRabbit", "7457008": "Kimo_X_Death", "7443110": "ShoopDaWoopBlAaa", "7451934": "ryan1981", "7443918": "TheTailsMinecart", "7488686": "Kawaii-Krab", "7469334": "MyScratchWeb4", "7489280": "wolf182", "7477854": "ScratchCreator160", "7445866": "Lhikan", "7462868": "frodobaggins7890", "7424968": "AntVennom", "7473756": "ThatOneTaco", "7492294": "Plantsking725", "7483240": "louwi-sotto", "7466008": "guy162", "7459080": "Greatgira", "7436096": "Minecraftviech", "7408464": "PixCraft", "7477580": "Chica909", "7499056": "vimio69", "7427104": "PoyoPoyo12345", "7452330": "-GinnyWeasley", "7447208": "piggert101", "7495440": "ausamurott", "7469560": "Quantanglement", "7469552": "-Simplex-", "7462382": "Mindrecre", "7413936": "Dragon_Wolf_Rookie", "7471756": "Princess_Twilight01", "7419728": "pokemonmasters23", "7490674": "jakelorimer5678", "7452996": "metaldragon12345", "7479822": "TaylorSwiftCrazy", "7420582": "OrangeAlex64", "7466522": "Spaer", "7494576": "andreipopa", "7476352": "MinecraftSIMPLIFIED", "7488316": "savetheblobfish", "7486744": "hoodiedude31", "7484916": "sinji555", "7483966": "-GET_REKT-", "7466214": "DIY_Scratcher", "7479294": "leiadog_test", "7475772": "Sunsetly", "7477678": "HerpdeDerp2", "7461722": "kitty1killer5", "7471274": "Galeptic", "7414102": "SomeoneRandom789", "7470062": "BonnieLas2004", "7469906": "Silent_Fortress", "7467778": "tuftDESIGN", "7465638": "ChespinRox1985", "7464794": "flowerlover888", "7458288": "SkratchU8", "7457758": "Augustly", "7455912": "YaNoMaybe", "7454864": "Brain-Games", "7454762": "TheUndertaker1", "7410080": "CAMOKA_TEST", "7430048": "selbyfan", "7419390": "TROLL_TEAM", "7420010": "marshmellow66", "7400696": "OMG200", "7456216": "PuisSang-soo", "7464838": "Pinksheep09", "7429988": "Nicolas1753", "7424486": "roberto789012", "7426142": "inkbolt01", "7459628": "atusi", "7481278": "nautokun", "7442482": "tsktnmc1230", "7459590": "shibashika", "7495472": "kcstar", "7436192": "yug_hctarcs", "7400536": "sharpheart", "7406398": "flora40370", "7474690": "DonnieLover1", "7444038": "Wolfe2015", "7484844": "happyargo", "7432702": "Gobo0221", "7412002": "PureMichigan", "7409488": "mbird123456789", "7471974": "caseyisthebest", "7468094": "liquidflame", "7442358": "cherrypop2005", "7429978": "PeaceLovePuppies", "7476442": "do_i_scare_u34", "7470868": "HarlemCreatorA", "7411680": "SaunceyWood1", "7463384": "Dark_Night", "7434628": "everton213"}