{"9467882": "yuina_iwasa", "9459294": "mongesan", "9433718": "yamatann", "9409994": "yonayoma", "9479254": "julia_728", "9479280": "karen777abc", "9485338": "Google001", "9467458": "Bootsietootsie", "9436074": "Foxish101", "9468920": "rawnewdlz", "9470452": "Botcho_Otkho", "9467912": "goofypuppy", "9407860": "Nano624", "9487340": "11georgera", "9459358": "stelllx", "9455694": "eggo3", "9478974": "saged360", "9410962": "leesunwoo8", "9456990": "bobobeans", "9472160": "gaby505", "9475316": "pinkieofthepies", "9409446": "Mlp-Seach-Light_12", "9464310": "codemasterthisum", "9474270": "Platformer123", "9455986": "happyzoomer", "9493110": "Guardian_Gold", "9415562": "TheNutterrr", "9455614": "aggo2", "9471098": "fashionpixie16", "9481996": "finleyisepic", "9449842": "FiddleFordMcGucket", "9471000": "honeybay08", "9434866": "Ethran10", "9456434": "Pixel_Ninja", "9476514": "nova2004koen", "9445428": "qhfx_bobby", "9495258": "ghostripper9876", "9466458": "derpymonster123"}